{
  "$schema": "https://schema.management.azure.com/schemas/2015-01-01/deploymentTemplate.json#",
  "contentVersion": "1.0.0.0",
  "parameters": {
    "adminUsername": {
      "type": "string",
      "metadata": {
        "description": "The Virtual Machine Dictator."
      }
    },
    "sshPublicKey": {
      "type": "string",
      "metadata": {
        "description": "SSH Public Key."
      }
    },
    "vmName": {
      "type": "string",
      "defaultValue": "",
      "metadata": {
        "description": "Virtual Machine Name."
      }
    },
    "dnsLabelPrefix": {
      "type": "string",
      "metadata": {
        "description": "Unique DNS Name for the Public IP used to access the Virtual Machine."
      }
    },
    "sourceIpAddress": {
      "type": "string",
      "defaultValue": "255.255.255.0/24",
      "metadata": {
        "description": "Source IP address for network security settings."
      }
    },
    "vmSku": {
      "type": "string",
      "defaultValue": "Standard_DS14_v2",
      "allowedValues": [
        "Standard_DS11_v2",
        "Standard_DS12_v2",
        "Standard_DS13_v2",
        "Standard_DS14_v2",
        "Standard_DS15_v2"
      ],
      "metadata": {
        "description": "Size of VM. See more on https://docs.microsoft.com/en-us/azure/virtual-machines/windows/sizes-memory"
      }
    },
    "ubuntuOSVersion": {
      "type": "string",
      "defaultValue": "16.04.0-LTS",
      "allowedValues": [
        "14.04.5-LTS",
        "15.10",
        "16.04.0-LTS"
      ],
      "metadata": {
        "description": "The Ubuntu version for the VM. This will pick a fully patched image of this given Ubuntu version."
      }
    }
  },
  "variables": {
    "diagnosticsStorageAccountName": "[concat(replace(toLower(resourceGroup().name), '-', ''), 'diag')]",
    "nicName": "[concat(parameters('vmName'), '-VMNic')]",
    "addressPrefix": "[variables('addressPrefix')]",
    "subnetName": "Subnet",
    "publicIPAddressName": "[concat(parameters('vmName'), '-IP')]",
    "vmName": "[parameters('vmName')]",
    "virtualNetworkName": "[concat(parameters('vmName'), '-VNET')]",
    "networkSecurityGroupName": "[concat(parameters('vmName'), '-NSG')]",
    "scriptsUri": "[uri(deployment().properties.templateLink.uri, '.')]"
  },
  "resources": [
    {
      "apiVersion": "[providers('Microsoft.Network','publicIPAddresses').apiVersions[0]]",
      "type": "Microsoft.Network/publicIPAddresses",
      "name": "[variables('publicIPAddressName')]",
      "location": "[resourceGroup().location]",
      "tags": {},
      "properties": {
        "publicIPAllocationMethod": "Dynamic",
        "idleTimeoutInMinutes": 30,
        "dnsSettings": {
          "domainNameLabel": "[parameters('dnsLabelPrefix')]"
        }
      },
      "dependsOn": []
    },
    {
      "apiVersion": "[providers('Microsoft.Network','networkSecurityGroups').apiVersions[0]]",
      "type": "Microsoft.Network/networkSecurityGroups",
      "name": "[variables('networkSecurityGroupName')]",
      "location": "[resourceGroup().location]",
      "tags": {},
      "properties": {
        "securityRules": [
          {
            "name": "default-allow-ssh",
            "properties": {
              "description": "Allows SSH traffic",
              "protocol": "TCP",
              "sourcePortRange": "*",
              "destinationPortRange": "22",
              "sourceAddressPrefix": "[parameters('sourceIpAddress')]",
              "destinationAddressPrefix": "*",
              "access": "Allow",
              "priority": 101,
              "direction": "Inbound"
            }
          }
        ]
      },
      "dependsOn": []
    },
    {
      "apiVersion": "[providers('Microsoft.Network','virtualNetworks').apiVersions[0]]",
      "type": "Microsoft.Network/virtualNetworks",
      "name": "[variables('virtualNetworkName')]",
      "location": "[resourceGroup().location]",
      "tags": {},
      "properties": {
        "addressSpace": {
          "addressPrefixes": [
            "[variables('addressPrefix')]"
          ]
        },
        "subnets": [
          {
            "name": "[variables('subnetName')]",
            "properties": {
              "addressPrefix": "[variables('addressPrefix')]",
              "networkSecurityGroup": {
                "id": "[resourceId('Microsoft.Network/networkSecurityGroups', variables('networkSecurityGroupName'))]"
              }
            }
          }
        ]
      },
      "dependsOn": [
        "[concat('Microsoft.Network/networkSecurityGroups/', variables('networkSecurityGroupName'))]"
      ]
    },
    {
      "apiVersion": "[providers('Microsoft.Network','networkInterfaces').apiVersions[0]]",
      "type": "Microsoft.Network/networkInterfaces",
      "name": "[variables('nicName')]",
      "location": "[resourceGroup().location]",
      "tags": {},
      "properties": {
        "ipConfigurations": [
          {
            "name": "ipconfig1",
            "properties": {
              "privateIPAllocationMethod": "Dynamic",
              "publicIPAddress": {
                "id": "[resourceId('Microsoft.Network/publicIPAddresses',variables('publicIPAddressName'))]"
              },
              "subnet": {
                "id": "[resourceId('Microsoft.Network/virtualNetworks/subnets', variables('virtualNetworkName'), variables('subnetName'))]"
              }
            }
          }
        ]
      },
      "dependsOn": [
        "[resourceId('Microsoft.Network/publicIPAddresses/', variables('publicIPAddressName'))]",
        "[resourceId('Microsoft.Network/virtualNetworks/', variables('virtualNetworkName'))]"
      ]
    },
    {
      "apiVersion": "[providers('Microsoft.Storage','storageAccounts').apiVersions[0]]",
      "type": "Microsoft.Storage/storageAccounts",
      "name": "[variables('diagnosticsStorageAccountName')]",
      "location": "[resourceGroup().location]",
      "sku": {
        "name": "Standard_LRS"
      },
      "kind": "StorageV2",
      "tags": {},
      "properties": {
        "supportsHttpsTrafficOnly": true,
        "encryption": {
          "services": {
            "file": {
              "enabled": true
            },
            "blob": {
              "enabled": true
            }
          },
          "keySource": "Microsoft.Storage"
        }
      },
      "dependsOn": []
    },
    {
      "apiVersion": "[providers('Microsoft.Compute','virtualMachines').apiVersions[0]]",
      "type": "Microsoft.Compute/virtualMachines",
      "name": "[variables('vmName')]",
      "location": "[resourceGroup().location]",
      "tags": {},
      "properties": {
        "hardwareProfile": {
          "vmSize": "[parameters('vmSku')]"
        },
        "osProfile": {
          "computerName": "[variables('vmName')]",
          "adminUsername": "[parameters('adminUsername')]",
          "linuxConfiguration": {
            "disablePasswordAuthentication": true,
            "ssh": {
              "publicKeys": [
                {
                  "path": "[concat('/home/', parameters('adminUsername'), '/.ssh/authorized_keys')]",
                  "keyData": "[concat('ssh-rsa ', parameters('sshPublicKey')]"
                }
              ]
            }
          },
          "secrets": []
        },
        "storageProfile": {
          "imageReference": {
            "publisher": "Canonical",
            "offer": "UbuntuServer",
            "sku": "[parameters('ubuntuOSVersion')]",
            "version": "latest"
          },
          "osDisk": {
            "name": "[concat(variables('vmName'),'_OsDisk_1')]",
            "osType": "Linux",
            "createOption": "FromImage",
            "caching": "ReadWrite",
            "managedDisk": {
              "storageAccountType": "Premium_LRS"
            },
            "diskSizeGB": 128
          },
          "dataDisks": [ ]
        },
        "networkProfile": {
          "networkInterfaces": [
            {
              "id": "[resourceId('Microsoft.Network/networkInterfaces', variables('nicName'))]"
            }
          ]
        },
        "diagnosticsProfile": {
          "bootDiagnostics": {
            "enabled": true,
            "storageUri": "[reference(resourceId('Microsoft.Storage/storageAccounts/', variables('diagnosticsStorageAccountName'))).primaryEndpoints.blob]"
          }
        }
      },
      "resources": [
        {
          "apiVersion": "[providers('Microsoft.Compute','virtualMachines/extensions').apiVersions[0]]",
          "type": "extensions",
          "name": "CustomScriptExtension",
          "location": "[resourceGroup().location]",
          "dependsOn": [
            "[resourceId('Microsoft.Compute/virtualMachines/', variables('vmName'))]"
          ],
          "properties": {
            "publisher": "Microsoft.Azure.Extensions",
            "type": "CustomScript",
            "typeHandlerVersion": "2.0",
            "autoUpgradeMinorVersion": true,
            "settings": {
              "fileUris": [
                "[concat(variables('scriptsUri'), 'init.sh')]"
              ]
            },
            "protectedSettings": {
              "commandToExecute": "[concat('sh init.sh ', parameters('adminUsername'))]"
            }
          }
        }
      ],
      "dependsOn": [
        "[resourceId('Microsoft.Storage/storageAccounts/', variables('diagnosticsStorageAccountName'))]",
        "[resourceId('Microsoft.Network/networkInterfaces/', variables('nicName'))]"
      ]
    }
  ],
  "outputs": {
    "hostname": {
      "type": "string",
      "value": "[reference(variables('publicIPAddressName')).dnsSettings.fqdn]"
    }
  }
}
